fds/__init__.py
fds/checkpoint.py
fds/cobalt.py
fds/compute.py
fds/cti_restart_io.py
fds/fds.py
fds/lsstan.py
fds/pbs.py
fds/segment.py
fds/slurm.py
fds/timedilation.py
fds/timeseries.py
fds-0.1.0.dev1.dist-info/DESCRIPTION.rst
fds-0.1.0.dev1.dist-info/METADATA
fds-0.1.0.dev1.dist-info/RECORD
fds-0.1.0.dev1.dist-info/WHEEL
fds-0.1.0.dev1.dist-info/metadata.json
fds-0.1.0.dev1.dist-info/top_level.txt
pascal_lite/__init__.py
pascal_lite/symbolic_value.py
pascal_lite/symbolic_variable.py
pascal_lite/operators/__init__.py
pascal_lite/operators/arithmetics.py
pascal_lite/operators/indexing.py
pascal_lite/operators/linalg.py
pascal_lite/operators/op_base.py
pascal_lite/operators/plinalg.py
pascal_lite/operators/shapes.py
