Metadata-Version: 2.0
Name: fds
Version: 0.1.0.dev1
Summary: Sensitivity analysis of chaotic simulations
Home-page: https://github.com/qiqi/fds
Author: Qiqi Wang
Author-email: qiqi.wang@gmail.com
License: GPL3
Keywords: sensitivity analysis chaotic simulation
Platform: UNKNOWN
Classifier: Development Status :: 2 - Pre-Alpha
Classifier: Intended Audience :: Developers
Classifier: Topic :: Scientific/Engineering
Classifier: License :: OSI Approved :: GNU General Public License v3 (GPLv3)
Classifier: Programming Language :: Python :: 2
Classifier: Programming Language :: Python :: 2.6
Classifier: Programming Language :: Python :: 2.7
Classifier: Programming Language :: Python :: 3
Classifier: Programming Language :: Python :: 3.3
Classifier: Programming Language :: Python :: 3.4
Classifier: Programming Language :: Python :: 3.5
Requires-Dist: dill
Requires-Dist: mpi4py (>=1.3.1)
Requires-Dist: numpy (>=1.10)
Requires-Dist: pytest
Requires-Dist: pytest-cov
Requires-Dist: python-coveralls
Requires-Dist: scipy (>=0.14)
